controlm_rest_api/__init__.py
controlm_rest_api/ctrlM.py
controlm_rest_api/library/__init__.py
controlm_rest_api/library/core.py
controlm_rest_api/settings/__init__.py
controlm_rest_api/settings/local.py
controlM_rest-0.1.9.dist-info/LICENSE.txt
controlM_rest-0.1.9.dist-info/METADATA
controlM_rest-0.1.9.dist-info/WHEEL
controlM_rest-0.1.9.dist-info/entry_points.txt
controlM_rest-0.1.9.dist-info/top_level.txt
controlM_rest-0.1.9.dist-info/RECORD
