Metadata-Version: 2.1
Name: controlM-rest
Version: 0.1.9
Summary: UNKNOWN
Home-page: UNKNOWN
License: UNKNOWN
Keywords: ControlM,REST-api
Platform: UNKNOWN
Requires-Python: >=2.7
Requires-Dist: requests (<3.0.0a0,>=2.8)
